colcon_cmake/__init__.py
colcon_cmake/argcomplete_completer/__init__.py
colcon_cmake/argcomplete_completer/cmake_args.py
colcon_cmake/environment/__init__.py
colcon_cmake/environment/cmake_module_path.py
colcon_cmake/environment/cmake_prefix_path.py
colcon_cmake/event_handler/__init__.py
colcon_cmake/event_handler/compile_commands.py
colcon_cmake/package_identification/__init__.py
colcon_cmake/package_identification/cmake.py
colcon_cmake/task/__init__.py
colcon_cmake/task/cmake/__init__.py
colcon_cmake/task/cmake/build.py
colcon_cmake/task/cmake/test.py
colcon_cmake/test_result/__init__.py
colcon_cmake/test_result/ctest.py
colcon_cmake-0.2.29.dist-info/LICENSE
colcon_cmake-0.2.29.dist-info/METADATA
colcon_cmake-0.2.29.dist-info/WHEEL
colcon_cmake-0.2.29.dist-info/entry_points.txt
colcon_cmake-0.2.29.dist-info/top_level.txt
colcon_cmake-0.2.29.dist-info/zip-safe
colcon_cmake-0.2.29.dist-info/RECORD
