Metadata-Version: 2.1
Name: colcon-cmake
Version: 0.2.29
Summary: Extension for colcon to support CMake packages.
Home-page: https://colcon.readthedocs.io
Author: Dirk Thomas
Author-email: web@dirk-thomas.net
Maintainer: Dirk Thomas, Michel Hidalgo
Maintainer-email: web@dirk-thomas.net, michel@ekumenlabs.com
License: Apache License, Version 2.0
Project-URL: Changelog, https://github.com/colcon/colcon-cmake/milestones?direction=desc&sort=due_date&state=closed
Project-URL: GitHub, https://github.com/colcon/colcon-cmake/
Keywords: colcon
Platform: UNKNOWN
Classifier: Development Status :: 3 - Alpha
Classifier: Environment :: Plugins
Classifier: Intended Audience :: Developers
Classifier: License :: OSI Approved :: Apache Software License
Classifier: Operating System :: MacOS
Classifier: Operating System :: Microsoft :: Windows
Classifier: Operating System :: POSIX
Classifier: Programming Language :: Python
Classifier: Topic :: Software Development :: Build Tools
Requires-Python: >=3.6
Provides-Extra: test
License-File: LICENSE
